sscws/__init__.py
sscws/__main__.py
sscws/bfieldmodels.py
sscws/cdf.py
sscws/conjunctions.py
sscws/coordinates.py
sscws/filteroptions.py
sscws/formatoptions.py
sscws/mapping.py
sscws/outputoptions.py
sscws/regions.py
sscws/request.py
sscws/result.py
sscws/sscws.py
sscws/timeinterval.py
sscws/tracing.py
sscws-2.4.6.dist-info/licenses/LICENSE
sscws-2.4.6.dist-info/METADATA
sscws-2.4.6.dist-info/WHEEL
sscws-2.4.6.dist-info/top_level.txt
sscws-2.4.6.dist-info/RECORD
