Metadata-Version: 2.4
Name: sscws
Version: 2.4.6
Summary: NASA's Satellite Situation Center Web Service Client Library
Home-page: https://berniegsfc.github.io/sscws/REST/
Author: Bernie Harris
Author-email: NASA-SPDF-Support@nasa.onmicrosoft.com
License: NOSA
Keywords: heliophysics,satellites,trajectories,orbits,location,conjunctions,earth magnetic field,ephemeris,space physics,spdf,ssc
Classifier: Development Status :: 5 - Production/Stable
Classifier: Environment :: Console
Classifier: Environment :: Web Environment
Classifier: Intended Audience :: End Users/Desktop
Classifier: Intended Audience :: Developers
Classifier: Intended Audience :: System Administrators
Classifier: License :: OSI Approved :: NASA Open Source Agreement v1.3 (NASA-1.3)
Classifier: Operating System :: OS Independent
Classifier: Programming Language :: Python
Classifier: Topic :: Scientific/Engineering :: Physics
Classifier: Topic :: Software Development :: Libraries :: Python Modules
License-File: LICENSE
Requires-Dist: python-dateutil>=2.8.0
Requires-Dist: requests>=2.20
Requires-Dist: numpy>=1.19.4
Provides-Extra: plot
Requires-Dist: matplotlib>=3.3.2; extra == "plot"
Provides-Extra: cdf
Requires-Dist: cdflib>=0.4.9; extra == "cdf"
Provides-Extra: cache
Requires-Dist: requests-cache>=1.2.1; extra == "cache"
Dynamic: author
Dynamic: author-email
Dynamic: classifier
Dynamic: description
Dynamic: description-content-type
Dynamic: home-page
Dynamic: keywords
Dynamic: license
Dynamic: license-file
Dynamic: provides-extra
Dynamic: requires-dist
Dynamic: summary
